{ "frames": {
   "0": {
    "frame": { "x": 0, "y": 0, "w": 256, "h": 256 },
    "rotated": false,
    "trimmed": false,
    "spriteSourceSize": { "x": 0, "y": 0, "w": 256, "h": 256 },
    "sourceSize": { "w": 256, "h": 256 },
    "duration": 500
   },
   "1": {
    "frame": { "x": 256, "y": 0, "w": 256, "h": 256 },
    "rotated": false,
    "trimmed": false,
    "spriteSourceSize": { "x": 0, "y": 0, "w": 256, "h": 256 },
    "sourceSize": { "w": 256, "h": 256 },
    "duration": 500
   },
   "2": {
    "frame": { "x": 512, "y": 0, "w": 256, "h": 256 },
    "rotated": false,
    "trimmed": false,
    "spriteSourceSize": { "x": 0, "y": 0, "w": 256, "h": 256 },
    "sourceSize": { "w": 256, "h": 256 },
    "duration": 250
   },
   "3": {
    "frame": { "x": 768, "y": 0, "w": 256, "h": 256 },
    "rotated": false,
    "trimmed": false,
    "spriteSourceSize": { "x": 0, "y": 0, "w": 256, "h": 256 },
    "sourceSize": { "w": 256, "h": 256 },
    "duration": 250
   },
   "4": {
    "frame": { "x": 1024, "y": 0, "w": 256, "h": 256 },
    "rotated": false,
    "trimmed": false,
    "spriteSourceSize": { "x": 0, "y": 0, "w": 256, "h": 256 },
    "sourceSize": { "w": 256, "h": 256 },
    "duration": 250
   },
   "5": {
    "frame": { "x": 1280, "y": 0, "w": 256, "h": 256 },
    "rotated": false,
    "trimmed": false,
    "spriteSourceSize": { "x": 0, "y": 0, "w": 256, "h": 256 },
    "sourceSize": { "w": 256, "h": 256 },
    "duration": 250
   },
   "6": {
    "frame": { "x": 1536, "y": 0, "w": 256, "h": 256 },
    "rotated": false,
    "trimmed": false,
    "spriteSourceSize": { "x": 0, "y": 0, "w": 256, "h": 256 },
    "sourceSize": { "w": 256, "h": 256 },
    "duration": 250
   },
   "7": {
    "frame": { "x": 1792, "y": 0, "w": 256, "h": 256 },
    "rotated": false,
    "trimmed": false,
    "spriteSourceSize": { "x": 0, "y": 0, "w": 256, "h": 256 },
    "sourceSize": { "w": 256, "h": 256 },
    "duration": 250
   },
   "8": {
    "frame": { "x": 2048, "y": 0, "w": 256, "h": 256 },
    "rotated": false,
    "trimmed": false,
    "spriteSourceSize": { "x": 0, "y": 0, "w": 256, "h": 256 },
    "sourceSize": { "w": 256, "h": 256 },
    "duration": 250
   },
   "9": {
    "frame": { "x": 2304, "y": 0, "w": 256, "h": 256 },
    "rotated": false,
    "trimmed": false,
    "spriteSourceSize": { "x": 0, "y": 0, "w": 256, "h": 256 },
    "sourceSize": { "w": 256, "h": 256 },
    "duration": 250
   },
   "10": {
    "frame": { "x": 2560, "y": 0, "w": 256, "h": 256 },
    "rotated": false,
    "trimmed": false,
    "spriteSourceSize": { "x": 0, "y": 0, "w": 256, "h": 256 },
    "sourceSize": { "w": 256, "h": 256 },
    "duration": 250
   },
   "11": {
    "frame": { "x": 2816, "y": 0, "w": 256, "h": 256 },
    "rotated": false,
    "trimmed": false,
    "spriteSourceSize": { "x": 0, "y": 0, "w": 256, "h": 256 },
    "sourceSize": { "w": 256, "h": 256 },
    "duration": 250
   },
   "12": {
    "frame": { "x": 3072, "y": 0, "w": 256, "h": 256 },
    "rotated": false,
    "trimmed": false,
    "spriteSourceSize": { "x": 0, "y": 0, "w": 256, "h": 256 },
    "sourceSize": { "w": 256, "h": 256 },
    "duration": 250
   }
 },
 "meta": {
  "app": "https://www.aseprite.org/",
  "version": "1.2.40",
  "image": "dummy13-scaled.png",
  "format": "RGBA8888",
  "size": { "w": 3328, "h": 256 },
  "scale": "1",
  "frameTags": [
   { "name": "idle", "from": 0, "to": 1, "direction": "pingpong" },
   { "name": "walk", "from": 2, "to": 4, "direction": "pingpong" },
   { "name": "pull", "from": 5, "to": 7, "direction": "pingpong" },
   { "name": "pushattack", "from": 8, "to": 10, "direction": "forward" },
   { "name": "downattack", "from": 11, "to": 11, "direction": "forward" },
   { "name": "upattack", "from": 12, "to": 12, "direction": "forward" }
  ],
  "layers": [
   { "name": "Layer 0", "opacity": 255, "blendMode": "normal" }
  ],
  "slices": [
  ]
 }
}
